LICENSE.md
README.md
pyproject.toml
src/dittolive/__init__.py
src/dittolive/__observer.py
src/dittolive/_utils.py
src/dittolive/ditto.py
src/dittolive/exceptions.py
src/dittolive/log.py
src/dittolive.egg-info/PKG-INFO
src/dittolive.egg-info/SOURCES.txt
src/dittolive.egg-info/dependency_links.txt
src/dittolive.egg-info/requires.txt
src/dittolive.egg-info/top_level.txt
src/dittolive/_transports/__init__.py
src/dittolive/_transports/sync_state.py
src/dittolive/_transports/transport_config.py
src/dittolive/_transports/transport_sync.py
src/dittolive/identity/__init__.py
src/dittolive/identity/identity.py
src/dittolive/identity/offline_playground.py
src/dittolive/identity/online_playground.py
src/dittolive/store/__init__.py
src/dittolive/store/__transaction.py
src/dittolive/store/abstract_document_path.py
src/dittolive/store/collection.py
src/dittolive/store/document.py
src/dittolive/store/document_id.py
src/dittolive/store/document_path.py
src/dittolive/store/live_query.py
src/dittolive/store/mutable_document.py
src/dittolive/store/mutable_document_path.py
src/dittolive/store/pending_id_specific_operation.py
src/dittolive/store/store.py
src/dittolive/store/subscription.py
src/dittolive/store/types.py
src/dittolive/store/update_result.py
tests/collection_test.py
tests/ditto_test.py
tests/document_test.py
tests/observer_test.py
tests/pending_id_specific_operation_test.py
tests/store_test.py
tests/transports_test.py
tests/utils.py