Metadata-Version: 2.1
Name: dittolive
Version: 0.0.3
Summary: Ditto Python SDK.
Author-email: Ditto Engineering Team <engineering@ditto.live>
License: Ditto Binary License
Project-URL: Documentation, https://docs.ditto.live
Project-URL: Changelog, https://docs.ditto.live/changelog
Keywords: database,P2P,CRDT
License-File: LICENSE.md
